CHANGES.rst
LICENSE.txt
MANIFEST.in
README.rst
setup.cfg
setup.py
bin/__init__.py
bin/fluid_stop_pumps.py
doc/changes.rst
doc/examples.rst
doc/index.rst
doc/install.rst
doc/linuxgpib.rst
doc/to_do.rst
doc/tutorials.rst
doc/examples/control_motor.rst
doc/examples/loop_with_1instr.rst
doc/examples/parallel_tasks.rst
doc/examples/session_instru.rst
fluidlab/__init__.py
fluidlab/_hg_rev.py
fluidlab/_version.py
fluidlab/output.py
fluidlab.egg-info/PKG-INFO
fluidlab.egg-info/SOURCES.txt
fluidlab.egg-info/dependency_links.txt
fluidlab.egg-info/requires.txt
fluidlab.egg-info/top_level.txt
fluidlab/daq/__init__.py
fluidlab/daq/daqmx.py
fluidlab/daq/streaming_t7.py
fluidlab/exp/__init__.py
fluidlab/exp/octavesession.py
fluidlab/exp/session.py
fluidlab/exp/test/__init__.py
fluidlab/exp/test/test_session.py
fluidlab/instruments/__init__.py
fluidlab/instruments/drivers.py
fluidlab/instruments/features.py
fluidlab/instruments/iec60488.py
fluidlab/instruments/amplifier/__init__.py
fluidlab/instruments/amplifier/stanford_sr830.py
fluidlab/instruments/chiller/__init__.py
fluidlab/instruments/chiller/julabo.py
fluidlab/instruments/chiller/lauda.py
fluidlab/instruments/chiller/thermocube.py
fluidlab/instruments/funcgen/__init__.py
fluidlab/instruments/funcgen/agilent_33220a.py
fluidlab/instruments/funcgen/agilent_33500b.py
fluidlab/instruments/funcgen/hp_33120a.py
fluidlab/instruments/funcgen/srs_ds360.py
fluidlab/instruments/funcgen/tektronix_afg3022b.py
fluidlab/instruments/funcgen/tti_tsx3510p.py
fluidlab/instruments/motor_controller/__init__.py
fluidlab/instruments/motor_controller/newport_xps_rl.py
fluidlab/instruments/motor_controller/unidrive_sp.py
fluidlab/instruments/multimeter/__init__.py
fluidlab/instruments/multimeter/hp_34401a.py
fluidlab/instruments/multimeter/mgc3.py
fluidlab/instruments/multimeter/mmr3.py
fluidlab/instruments/multimeter/neel_lhlm.py
fluidlab/instruments/multimeter/thorlabs_s110.py
fluidlab/instruments/multiplexer/__init__.py
fluidlab/instruments/multiplexer/agilent_34970a.py
fluidlab/instruments/multiplexer/cryocon_24c.py
fluidlab/instruments/multiplexer/keithley_2700.py
