Metadata-Version: 2.1
Name: fluidlab
Version: 0.1.0
Summary: Framework for studying fluid dynamics by experiments.
Home-page: https://bitbucket.org/paugier/fluiddyn
Author: Pierre Augier
Author-email: pierre.augier@legi.cnrs.fr
License: CeCILL-B
Keywords: Fluid dynamics,research
Platform: UNKNOWN
Classifier: Development Status :: 5 - Production/Stable
Classifier: Intended Audience :: Science/Research
Classifier: Intended Audience :: Education
Classifier: Topic :: Scientific/Engineering
Classifier: License :: OSI Approved :: BSD License
Classifier: Programming Language :: Python
Classifier: Programming Language :: Python :: 3
Classifier: Programming Language :: Python :: 3.6
Classifier: Programming Language :: Python :: 3.7
Classifier: Programming Language :: Cython
Provides-Extra: test
Provides-Extra: doc
Provides-Extra: dev
